datamuse_cli/__init__.py
datamuse_cli/__main__.py
datamuse_cli/cli.py
datamuse_cli-0.0.3.dist-info/METADATA
datamuse_cli-0.0.3.dist-info/WHEEL
datamuse_cli-0.0.3.dist-info/entry_points.txt
datamuse_cli-0.0.3.dist-info/top_level.txt
datamuse_cli-0.0.3.dist-info/RECORD
