Metadata-Version: 2.1
Name: datamuse-cli
Version: 0.0.3
Summary: A command line interface that displays results from the Datamuse API
Home-page: https://github.com/agmmnn/datamuse-cli
Author: agmmnn
Classifier: Programming Language :: Python :: 3
Classifier: Operating System :: OS Independent
Classifier: Environment :: Console
Classifier: Topic :: Utilities
Requires-Python: >=3.6.3
Requires-Dist: rich
Requires-Dist: aiohttp
